{"__v":0,"_id":{"$oid":"568bc380e1984b9d22496f2d"},"class":"revolution-mch-1","elems":[{"bgfit":"cover","bgposition":"center center","bgrepeat":"no-repeat","src":"/api/images/slide/slide1_720x270.jpg","tag":"img"},{"_iac":"sft","class":"tp-caption revolution-ch1 font-ming","easing":"Power3.easeIn","endeasing":"Power1.easeIn","endspeed":300,"hoffset":0,"html":"\u003cp class=\"color-light\"\u003e OFF 漫遊純淨紐西蘭 \u003c/p\u003e","speed":1500,"start":500,"tag":"div","voffset":135,"x":"center","y":"top"},{"_iac":"sft","captionhidden":"off","class":"tp-caption slide-font-32 font-ming","easing":"Power4.easeOut","endeasing":"Power1.easeIn","endspeed":300,"hoffset":0,"html":"\u003cdiv class=\"color-light\" style=\"border-color: white; border: solid 1px; padding: 5px;\"\u003e 蜜月佳偶及現場報名\u003cbr\u003e 即可獲得神祕小禮！ \u003c/div\u003e","speed":1600,"start":1800,"tag":"div","x":"right","y":"center"},{"captionhidden":"off","class":"tp-caption lfl revolution-ch1 font-ming","easing":"Power4.easeOut","endeasing":"Power1.easeIn","endspeed":100,"hoffset":0,"html":"\u003cdiv style=\"border-color: white; border-top: solid 1px; border-bottom: solid 3px; padding: 5px;\"\u003e \u003cp class=\"color-light\"\u003e 2015-2016年 \u003c/p\u003e \u003cstrong class=\"color-light\" style=\"font-size: 80%;\"\u003e 【OFF慢遊】系列 紐西蘭行程發表會 \u003c/strong\u003e \u003c/div\u003e","speed":1600,"start":2300,"tag":"div","voffset":-50,"x":0,"y":"center"},{"captionhidden":"off","class":"tp-caption lfb revolution-ch1 font-ming","easing":"Power4.easeOut","endeasing":"Power1.easeIn","endspeed":100,"hoffset":0,"html":"\u003cdiv style=\"border-color: white; border-top: solid 3px; border-bottom: solid 1px; padding: 5px;\"\u003e \u003cp class=\"color-light\"\u003e 時間：2015/10/17 下午2:00PM \u003c/p\u003e \u003cp class=\"color-light\"\u003e 地點：樂遊旅行社2樓 會議室 \u003c/p\u003e \u003c/div\u003e","speed":1600,"start":2800,"tag":"div","voffset":150,"x":0,"y":"center"}],"masterspeed":1000,"slotamount":5,"title":"OFF 漫遊純淨紐西蘭","transition":"fade"}
{"__v":0,"_id":{"$oid":"568bc6517cff55cb23bc29f7"},"class":"revolution-mch-1","elems":[{"bgfit":"cover","bgposition":"center top","bgrepeat":"no-repeat","src":"/api/images/slide/slide2_1280x547.jpg","tag":"img"},{"class":"tp-caption lft slide-font-50","easing":"Power4.easeIn","endeasing":"Power1.easeIn","endspeed":300,"hoffset":0,"html":"\u003cp class=\"color-light\"\u003e 戶外活動深度紐西蘭 \u003c/p\u003e","speed":2000,"start":500,"tag":"div","voffset":135,"x":"center","y":"top"},{"class":"tp-caption revolution-ch1 lfr font-ming","easing":"Power1.easeIn","endeasing":"Power1.easeIn","endspeed":300,"hoffset":0,"html":"\u003cdiv class=\"tag-box tag-box-v2\" style=\"background-color: rgba(250,250,250,0.45)\"\u003e \u003cp class=\"color-black\"\u003e 2015-2016 年 \u003c/p\u003e \u003cp style=\"color: #b63629; font-size: 120%; padding-bottom: 20px;\"\u003e 戶外活動系列紐西蘭行程發表會 \u003c/p\u003e \u003cp class=\"color-black\"\u003e 時間: 2015/10/7 下午 2:00 PM \u003c/p\u003e \u003cp class=\"color-black\"\u003e 地點: 樂遊旅行社2樓 會議室 \u003c/p\u003e \u003c/div\u003e","speed":2000,"start":1000,"tag":"div","voffset":40,"x":"right","y":"bottom"}],"masterspeed":1000,"slotamount":5,"title":"戶外活動深度紐西蘭","transition":"fade"}
{"__v":0,"_id":{"$oid":"568bc6887cff55cb23bc29f8"},"class":"revolution-mch-1","elems":[{"bgfit":"cover","bgposition":"center top","bgrepeat":"no-repeat","src":"/api/images/slide/slide3.png","tag":"img"}],"masterspeed":1000,"slotamount":5,"title":"南極探險船 海典感恩號16天","transition":"fade"}
{"__v":0,"_id":{"$oid":"568bc6bc7cff55cb23bc29f9"},"class":"revolution-mch-1","elems":[{"bgfit":"cover","bgposition":"center top","bgrepeat":"no-repeat","src":"/api/images/slide/slide4.png","tag":"img"}],"masterspeed":1000,"slotamount":5,"title":"北歐極光屋、破冰船\u0026帝王蟹之旅10日","transition":"fade"}
{"__v":0,"_id":{"$oid":"568bc6ff7cff55cb23bc29fa"},"class":"revolution-mch-1","elems":[{"bgfit":"cover","bgposition":"center top","bgrepeat":"no-repeat","src":"/api/images/slide/slide5.png","tag":"img"}],"masterspeed":1000,"slotamount":5,"title":"西班牙11天夢想之旅","transition":"fade"}
